MANIFEST.in
README.rst
setup.py
collective/__init__.py
collective.actions.delete.egg-info/PKG-INFO
collective.actions.delete.egg-info/SOURCES.txt
collective.actions.delete.egg-info/dependency_links.txt
collective.actions.delete.egg-info/entry_points.txt
collective.actions.delete.egg-info/namespace_packages.txt
collective.actions.delete.egg-info/not-zip-safe
collective.actions.delete.egg-info/requires.txt
collective.actions.delete.egg-info/top_level.txt
collective/actions/__init__.py
collective/actions/delete/README.txt
collective/actions/delete/__init__.py
collective/actions/delete/browser.py
collective/actions/delete/configure.zcml
collective/actions/delete/interfaces.py
collective/actions/delete/tests.py
collective/actions/delete/version.txt
collective/actions/delete/locales/de/LC_MESSAGES/collective.actions.delete.po
collective/actions/delete/locales/fr/LC_MESSAGES/collective.actions.delete.po
collective/actions/delete/locales/nl/LC_MESSAGES/collective.actions.delete.po
collective/actions/delete/profiles/default/actions.xml
collective/actions/delete/templates/confirmation.pt
docs/HISTORY.txt
docs/INSTALL.txt
docs/LICENSE.GPL
docs/LICENSE.txt