Metadata-Version: 1.1
Name: collective.actions.delete
Version: 0.1.4
Summary: Delete items in folder content with confirmation
Home-page: https://svn.plone.org/svn/collective/collective.actions.delete
Author: Ingeniweb
Author-email: support@ingeniweb.com
License: GPL
Keywords: folder delete confirmation
Platform: UNKNOWN
Classifier: Programming Language :: Python
Classifier: Programming Language :: Python :: 2.6
Classifier: Programming Language :: Python :: 2.7
Classifier: Framework :: Plone
Classifier: Framework :: Plone :: 4.3
Classifier: Framework :: Plone :: 4.1
Classifier: Programming Language :: Python
Classifier: Topic :: Software Development :: Libraries :: Python Modules
